lp_api_wrapper/__init__.py
lp_api_wrapper/apis/__init__.py
lp_api_wrapper/apis/admin_users.py
lp_api_wrapper/apis/agent_groups.py
lp_api_wrapper/apis/agent_metrics.py
lp_api_wrapper/apis/away_reason.py
lp_api_wrapper/apis/engagement_history.py
lp_api_wrapper/apis/messaging_interactions.py
lp_api_wrapper/apis/messaging_operations.py
lp_api_wrapper/apis/operational_realtime.py
lp_api_wrapper/apis/predefined_categories.py
lp_api_wrapper/apis/predefined_content.py
lp_api_wrapper/apis/skills.py
lp_api_wrapper/logins/__init__.py
lp_api_wrapper/logins/oauth_login.py
lp_api_wrapper/logins/user_login.py
lp_api_wrapper/parsers/__init__.py
lp_api_wrapper/parsers/engagement_history/__init__.py
lp_api_wrapper/parsers/engagement_history/events.py
lp_api_wrapper/parsers/engagement_history/parse_engagements.py
lp_api_wrapper/parsers/messaging_interactions/__init__.py
lp_api_wrapper/parsers/messaging_interactions/events.py
lp_api_wrapper/parsers/messaging_interactions/parse_conversations.py
lp_api_wrapper/sqlite/__init__.py
lp_api_wrapper/sqlite/engagement_history_db/__init__.py
lp_api_wrapper/sqlite/engagement_history_db/db_model.py
lp_api_wrapper/sqlite/engagement_history_db/engagement_history_db.py
lp_api_wrapper/sqlite/messaging_interactions_db/__init__.py
lp_api_wrapper/sqlite/messaging_interactions_db/db_model.py
lp_api_wrapper/sqlite/messaging_interactions_db/messaging_interactions_db.py
lp_api_wrapper/util/__init__.py
lp_api_wrapper/util/domain_service.py
lp_api_wrapper/util/wrapper_base.py
lp_api_wrapper-0.6.6.dist-info/METADATA
lp_api_wrapper-0.6.6.dist-info/WHEEL
lp_api_wrapper-0.6.6.dist-info/top_level.txt
lp_api_wrapper-0.6.6.dist-info/RECORD
