Metadata-Version: 2.1
Name: lp-api-wrapper
Version: 0.6.6
Summary: Unofficial LP Data API Wrapper
Home-page: https://github.com/danielkerwin/lp-api-wrapper
Author: LivePerson
Author-email: analytics@liveperson.com
License: MIT
Platform: UNKNOWN
Classifier: License :: OSI Approved :: MIT License
Classifier: Programming Language :: Python :: 3
Classifier: Programming Language :: Python :: 3.6
Requires-Dist: requests
Requires-Dist: pandas
Requires-Dist: requests-oauthlib
Requires-Dist: peewee
